pylembic/__init__.py
pylembic/cli.py
pylembic/exceptions.py
pylembic/formatter.py
pylembic/logger.py
pylembic/validator.py
pylembic-0.8.0.dist-info/METADATA
pylembic-0.8.0.dist-info/WHEEL
pylembic-0.8.0.dist-info/entry_points.txt
pylembic-0.8.0.dist-info/licenses/LICENSE
pylembic-0.8.0.dist-info/RECORD
