Metadata-Version: 2.4
Name: pylembic
Version: 0.8.0
Summary: This package provides validation for Alembic migrations.
Author-email: Marco Espinosa <marco@marcoespinosa.com>
License: MIT License
License-File: LICENSE
Requires-Python: >=3.11
Requires-Dist: alembic==1.16.5
Requires-Dist: networkx==3.5
Requires-Dist: typer==0.17.4
Provides-Extra: all
Requires-Dist: matplotlib==3.10.6; extra == 'all'
Provides-Extra: standard
